holms/__init__.py
holms/__main__.py
holms/_version.py
holms/cli/__init__.py
holms/cli/common.py
holms/cli/entrypoint.py
holms/cmd/__init__.py
holms/cmd/format.py
holms/cmd/legend.py
holms/cmd/path.py
holms/cmd/run.py
holms/cmd/version.py
holms/core/__init__.py
holms/core/attr.py
holms/core/cats.py
holms/core/char.py
holms/core/opt.py
holms/core/reader.py
holms/core/view.py
holms/core/writer.py
holms/data/all-cats.bin
holms/data/all-cats.sh
holms/data/format.ptpl
holms/db/__init__.py
holms/db/ascii_cc.py
holms/db/ucblk.py
holms/db/uccat.py
holms/shared/__init__.py
holms/shared/log.py
holms/shared/scale.py
holms/shared/util.py
holms-1.6.0.dist-info/METADATA
holms-1.6.0.dist-info/WHEEL
holms-1.6.0.dist-info/entry_points.txt
holms-1.6.0.dist-info/RECORD
